cli.py
root_signals_cli-0.1.3.dist-info/METADATA
root_signals_cli-0.1.3.dist-info/WHEEL
root_signals_cli-0.1.3.dist-info/entry_points.txt
root_signals_cli-0.1.3.dist-info/top_level.txt
root_signals_cli-0.1.3.dist-info/RECORD
